pyGizwits/Exceptions.py
pyGizwits/GizwitsClient.py
pyGizwits/GizwitsDevice.py
pyGizwits/WebSocketConnection.py
pyGizwits/__about__.py
pyGizwits/__init__.py
pyGizwits/pyGizwits.py
pygizwits-0.0.3.dist-info/METADATA
pygizwits-0.0.3.dist-info/WHEEL
pygizwits-0.0.3.dist-info/licenses/LICENSE
pygizwits-0.0.3.dist-info/RECORD
