Metadata-Version: 2.1
Name: pyGizwits
Version: 0.0.3
Summary: A wrapper for Gizwits OpenAPI and websocket API
Project-URL: Documentation, https://github.com/brendann993/pyGizwits#readme
Project-URL: Issues, https://github.com/brendann993/pyGizwits/issues
Project-URL: Source, https://github.com/brendann993/pyGizwits
Project-URL: Download, https://github.com/brendann993/pyGizwits/releases
Author-email: brendann993 <brendann993@icloud.com>
License-Expression: MIT
License-File: LICENSE
Classifier: Development Status :: 4 - Beta
Classifier: Programming Language :: Python
Classifier: Programming Language :: Python :: 3.7
Classifier: Programming Language :: Python :: 3.8
Classifier: Programming Language :: Python :: 3.9
Classifier: Programming Language :: Python :: 3.10
Classifier: Programming Language :: Python :: 3.11
Classifier: Programming Language :: Python :: Implementation :: CPython
Classifier: Programming Language :: Python :: Implementation :: PyPy
Requires-Python: >=3.7
Requires-Dist: aiohttp
Requires-Dist: pyee
